{"is_source_file": true, "format": "C++ header file", "description": "This header file defines the Theme namespace which provides theme-related constants, styles, and helper functions for styling UI components in a Qt-based application. It includes color definitions, font styles, shadow and radius settings, and functions returning style sheets for UI elements like cards, buttons, inputs, and list items.", "external_files": ["<QString>", "<QColor>", "<QFont>"], "external_methods": ["QString::arg", "QFont::setPointSize", "QFont::setBold", "QColor::name"], "published": ["Theme::Primary", "Theme::Secondary", "Theme::Success", "Theme::Error", "Theme::Background", "Theme::Surface", "Theme::Text", "Theme::RadiusSmall", "Theme::RadiusMedium", "Theme::RadiusLarge", "Theme::headingFont", "Theme::bodyFont", "Theme::cardStyle", "Theme::pillButtonStyle", "Theme::inputStyle", "Theme::listItemStyle"], "classes": [], "methods": [{"name": "QFont headingFont(int size=20,bool bold=true)", "description": "Returns a QFont object configured for headings with specified size and boldness.", "scope": "Theme", "scopeKind": "namespace"}, {"name": "QFont bodyFont(int size=12,bool bold=false)", "description": "Returns a QFont object configured for body text with specified size and weight.", "scope": "Theme", "scopeKind": "namespace"}, {"name": "QString cardStyle()", "description": "Provides a style sheet string for card-like UI components with background, border, padding, and radius.", "scope": "Theme", "scopeKind": "namespace"}, {"name": "QString pillButtonStyle(const QColor & bg,const QColor & fg=QColor (\"#ffffff\"))", "description": "Provides a style sheet string for pill-shaped buttons with specified background and foreground colors.", "scope": "Theme", "scopeKind": "namespace"}, {"name": "QString inputStyle()", "description": "Returns a style sheet string for input fields with background, border, padding, and focus styles.", "scope": "Theme", "scopeKind": "namespace"}, {"name": "QString listItemStyle()", "description": "Provides a style sheet string for list items with background, border, and radius.", "scope": "Theme", "scopeKind": "namespace"}], "calls": ["QString::arg", "QFont::setPointSize", "QFont::setBold", "QColor::name"], "search-terms": ["Theme namespace", "Qt style helper", "Color constants", "Fonts", "QColor", "QFont", "style sheets", "UI theming Qt"], "state": 2, "file_id": 4, "knowledge_revision": 9, "git_revision": "", "ctags": [{"_type": "tag", "name": "Background", "path": "/home/kavia/workspace/code-generation/recipe-explorer-38527-38546/recipe_native_app/include/theme.h", "pattern": "/^    static const QColor Background(\"#f9fafb\");$/", "language": "C++", "typeref": "typename:const QColor", "kind": "variable", "scope": "Theme", "scopeKind": "namespace"}, {"_type": "tag", "name": "Error", "path": "/home/kavia/workspace/code-generation/recipe-explorer-38527-38546/recipe_native_app/include/theme.h", "pattern": "/^    static const QColor Error(\"#EF4444\");$/", "language": "C++", "typeref": "typename:const QColor", "kind": "variable", "scope": "Theme", "scopeKind": "namespace"}, {"_type": "tag", "name": "Primary", "path": "/home/kavia/workspace/code-generation/recipe-explorer-38527-38546/recipe_native_app/include/theme.h", "pattern": "/^    static const QColor Primary(\"#2563EB\");$/", "language": "C++", "typeref": "typename:const QColor", "kind": "variable", "scope": "Theme", "scopeKind": "namespace"}, {"_type": "tag", "name": "RadiusLarge", "path": "/home/kavia/workspace/code-generation/recipe-explorer-38527-38546/recipe_native_app/include/theme.h", "pattern": "/^    static const int RadiusLarge = 16;$/", "language": "C++", "typeref": "typename:const int", "kind": "variable", "scope": "Theme", "scopeKind": "namespace"}, {"_type": "tag", "name": "RadiusMedium", "path": "/home/kavia/workspace/code-generation/recipe-explorer-38527-38546/recipe_native_app/include/theme.h", "pattern": "/^    static const int RadiusMedium = 12;$/", "language": "C++", "typeref": "typename:const int", "kind": "variable", "scope": "Theme", "scopeKind": "namespace"}, {"_type": "tag", "name": "RadiusSmall", "path": "/home/kavia/workspace/code-generation/recipe-explorer-38527-38546/recipe_native_app/include/theme.h", "pattern": "/^    static const int RadiusSmall = 8;$/", "language": "C++", "typeref": "typename:const int", "kind": "variable", "scope": "Theme", "scopeKind": "namespace"}, {"_type": "tag", "name": "Secondary", "path": "/home/kavia/workspace/code-generation/recipe-explorer-38527-38546/recipe_native_app/include/theme.h", "pattern": "/^    static const QColor Secondary(\"#F59E0B\");$/", "language": "C++", "typeref": "typename:const QColor", "kind": "variable", "scope": "Theme", "scopeKind": "namespace"}, {"_type": "tag", "name": "Success", "path": "/home/kavia/workspace/code-generation/recipe-explorer-38527-38546/recipe_native_app/include/theme.h", "pattern": "/^    static const QColor Success(\"#F59E0B\");$/", "language": "C++", "typeref": "typename:const QColor", "kind": "variable", "scope": "Theme", "scopeKind": "namespace"}, {"_type": "tag", "name": "Surface", "path": "/home/kavia/workspace/code-generation/recipe-explorer-38527-38546/recipe_native_app/include/theme.h", "pattern": "/^    static const QColor Surface(\"#ffffff\");$/", "language": "C++", "typeref": "typename:const QColor", "kind": "variable", "scope": "Theme", "scopeKind": "namespace"}, {"_type": "tag", "name": "THEME_H", "path": "/home/kavia/workspace/code-generation/recipe-explorer-38527-38546/recipe_native_app/include/theme.h", "pattern": "/^#define THEME_H$/", "language": "C++", "kind": "macro"}, {"_type": "tag", "name": "Text", "path": "/home/kavia/workspace/code-generation/recipe-explorer-38527-38546/recipe_native_app/include/theme.h", "pattern": "/^    static const QColor Text(\"#111827\");$/", "language": "C++", "typeref": "typename:const QColor", "kind": "variable", "scope": "Theme", "scopeKind": "namespace"}, {"_type": "tag", "name": "Theme", "path": "/home/kavia/workspace/code-generation/recipe-explorer-38527-38546/recipe_native_app/include/theme.h", "pattern": "/^namespace Theme {$/", "language": "C++", "kind": "namespace"}, {"_type": "tag", "name": "bodyFont", "path": "/home/kavia/workspace/code-generation/recipe-explorer-38527-38546/recipe_native_app/include/theme.h", "pattern": "/^    inline QFont bodyFont(int size = 12, bool bold = false) {$/", "language": "C++", "typeref": "typename:QFont", "kind": "function", "signature": "(int size=12,bool bold=false)", "scope": "Theme", "scopeKind": "namespace"}, {"_type": "tag", "name": "cardStyle", "path": "/home/kavia/workspace/code-generation/recipe-explorer-38527-38546/recipe_native_app/include/theme.h", "pattern": "/^    inline QString cardStyle() {$/", "language": "C++", "typeref": "typename:QString", "kind": "function", "signature": "()", "scope": "Theme", "scopeKind": "namespace"}, {"_type": "tag", "name": "headingFont", "path": "/home/kavia/workspace/code-generation/recipe-explorer-38527-38546/recipe_native_app/include/theme.h", "pattern": "/^    inline QFont headingFont(int size = 20, bool bold = true) {$/", "language": "C++", "typeref": "typename:QFont", "kind": "function", "signature": "(int size=20,bool bold=true)", "scope": "Theme", "scopeKind": "namespace"}, {"_type": "tag", "name": "inputStyle", "path": "/home/kavia/workspace/code-generation/recipe-explorer-38527-38546/recipe_native_app/include/theme.h", "pattern": "/^    inline QString inputStyle() {$/", "language": "C++", "typeref": "typename:QString", "kind": "function", "signature": "()", "scope": "Theme", "scopeKind": "namespace"}, {"_type": "tag", "name": "listItemStyle", "path": "/home/kavia/workspace/code-generation/recipe-explorer-38527-38546/recipe_native_app/include/theme.h", "pattern": "/^    inline QString listItemStyle() {$/", "language": "C++", "typeref": "typename:QString", "kind": "function", "signature": "()", "scope": "Theme", "scopeKind": "namespace"}, {"_type": "tag", "name": "pillButtonStyle", "path": "/home/kavia/workspace/code-generation/recipe-explorer-38527-38546/recipe_native_app/include/theme.h", "pattern": "/^    inline QString pillButtonStyle(const QColor &bg, const QColor &fg = QColor(\"#ffffff\")) {$/", "language": "C++", "typeref": "typename:QString", "kind": "function", "signature": "(const QColor & bg,const QColor & fg=QColor (\"#ffffff\"))", "scope": "Theme", "scopeKind": "namespace"}], "hash": "c54c985dd1d7da37640b417016d23608", "format-version": 4, "code-base-name": "recipe_native_app", "filename": "recipe_native_app/include/theme.h", "fields": [{"name": "const QColor Background", "scope": "Theme", "scopeKind": "namespace", "description": "unavailable"}, {"name": "const QColor Error", "scope": "Theme", "scopeKind": "namespace", "description": "unavailable"}, {"name": "const QColor Primary", "scope": "Theme", "scopeKind": "namespace", "description": "unavailable"}, {"name": "const int RadiusLarge", "scope": "Theme", "scopeKind": "namespace", "description": "unavailable"}, {"name": "const int RadiusMedium", "scope": "Theme", "scopeKind": "namespace", "description": "unavailable"}, {"name": "const int RadiusSmall", "scope": "Theme", "scopeKind": "namespace", "description": "unavailable"}, {"name": "const QColor Secondary", "scope": "Theme", "scopeKind": "namespace", "description": "unavailable"}, {"name": "const QColor Success", "scope": "Theme", "scopeKind": "namespace", "description": "unavailable"}, {"name": "const QColor Surface", "scope": "Theme", "scopeKind": "namespace", "description": "unavailable"}, {"name": "const QColor Text", "scope": "Theme", "scopeKind": "namespace", "description": "unavailable"}], "revision_history": [{"9": ""}]}